fastapptest/__init__.py
fastapptest/cli/__init__.py
fastapptest/cli/auth_helpers.py
fastapptest/cli/batch_runner.py
fastapptest/cli/ci_runner.py
fastapptest/cli/input_helpers.py
fastapptest/cli/interactive_runner.py
fastapptest/cli/main.py
fastapptest/cli/manual_runner.py
fastapptest/cli/schema_validator.py
fastapptest/config/__init__.py
fastapptest/config/defaults.py
fastapptest/core/__init__.py
fastapptest/core/ast_parser.py
fastapptest/core/endpoint_extractor.py
fastapptest/core/fastapi_detector.py
fastapptest/core/payload_generator.py
fastapptest/core/project_scanner.py
fastapptest/core/reporting.py
fastapptest/core/request_context.py
fastapptest/core/request_executor.py
fastapptest/core/schema_extractor.py
fastapptest/core/test_generator.py
fastapptest/core/test_runner.py
fastapptest/core/validators.py
fastapptest/models/__init__.py
fastapptest/models/ast_utils.py
fastapptest/models/logger.py
fastapptest/models/path_filters.py
fastapptest/old_app/src/old_app/__init__.py
fastapptest/old_app/src/old_app/config.py
fastapptest/old_app/src/old_app/database.py
fastapptest/old_app/src/old_app/main.py
fastapptest/old_app/src/old_app/core/__init__.py
fastapptest/old_app/src/old_app/core/security.py
fastapptest/old_app/src/old_app/models/__init__.py
fastapptest/old_app/src/old_app/models/user.py
fastapptest/old_app/src/old_app/routers/__init__.py
fastapptest/old_app/src/old_app/routers/auth.py
fastapptest/old_app/src/old_app/routers/users.py
fastapptest/old_app/src/old_app/schemas/__init__.py
fastapptest/old_app/src/old_app/schemas/user.py
fastapptest/runners/__init__.py
fastapptest/runners/local_runner.py
fastapptest/runners/pytestrunner.py
fastapptest/tests/test_ast_parser.py
fastapptest/tests/test_endpoint_extractor.py
fastapptest/tests/test_fastapi_detector.py
fastapptest/tests/test_payload_generator.py
fastapptest/tests/test_project_scanner.py
fastapptest/tests/test_schema_extractor.py
fastapptest/tests/test_test_generator.py
fastapptest-2.0.0.dist-info/licenses/LICENSE
fastapptest-2.0.0.dist-info/METADATA
fastapptest-2.0.0.dist-info/WHEEL
fastapptest-2.0.0.dist-info/entry_points.txt
fastapptest-2.0.0.dist-info/top_level.txt
fastapptest-2.0.0.dist-info/RECORD
