Metadata-Version: 2.4
Name: fastapptest
Version: 2.0.0
Summary: Schema-aware automated testing for FastAPI applications
Author: Ganesh Nalawade
License: MIT
Keywords: FastAPI,Testing,CI/CD,Automated Tests,Pydantic,API Testing
Classifier: Development Status :: 5 - Production/Stable
Classifier: Intended Audience :: Developers
Classifier: License :: OSI Approved :: MIT License
Classifier: Programming Language :: Python :: 3
Classifier: Programming Language :: Python :: 3.9
Classifier: Programming Language :: Python :: 3.10
Classifier: Framework :: FastAPI
Classifier: Topic :: Software Development :: Testing
Requires-Python: >=3.9
License-File: LICENSE
Requires-Dist: fastapi>=0.95
Requires-Dist: pydantic>=1.10
Requires-Dist: requests>=2.28
Requires-Dist: httpx>=0.24
Dynamic: license-file
